setup.cfg
setup.py
NewLavaAPI/NewLavaAPI.py
NewLavaAPI/__init__.py
NewLavaAPI.egg-info/PKG-INFO
NewLavaAPI.egg-info/SOURCES.txt
NewLavaAPI.egg-info/dependency_links.txt
NewLavaAPI.egg-info/not-zip-safe
NewLavaAPI.egg-info/top_level.txt