Metadata-Version: 2.1
Name: NewLavaAPI
Version: 1.1
Summary: New Lib for LavaAPI
Home-page: UNKNOWN
Author-email: banjiro_me@cyclonesoftware.space
License: UNKNOWN
Platform: UNKNOWN
